imow_webapi-0.8.4-py3.12-nspkg.pth
imow/api/__init__.py
imow/common/__init__.py
imow/common/actions.py
imow/common/consts.py
imow/common/exceptions.py
imow/common/messages.py
imow/common/mowerstate.py
imow/common/package_descriptions.py
imow_webapi-0.8.4.dist-info/LICENSE
imow_webapi-0.8.4.dist-info/METADATA
imow_webapi-0.8.4.dist-info/WHEEL
imow_webapi-0.8.4.dist-info/entry_points.txt
imow_webapi-0.8.4.dist-info/namespace_packages.txt
imow_webapi-0.8.4.dist-info/top_level.txt
imow_webapi-0.8.4.dist-info/RECORD
