Metadata-Version: 2.1
Name: imow-webapi
Version: 0.8.4
Summary: A library to authenticate and interact with STIHL iMow mowers using their WebAPI
Home-page: https://github.com/ChrisHaPunkt/stihl-imow-webapi
Author: ChrisHaPunkt
License: GPL
Keywords: stihl imow mower api
Classifier: Development Status :: 4 - Beta
Classifier: Intended Audience :: Developers
Classifier: License :: OSI Approved :: MIT License
Classifier: Topic :: Software Development :: Libraries :: Python Modules
Classifier: Programming Language :: Python :: 3
Classifier: Programming Language :: Python :: 3.10
Classifier: Programming Language :: Python :: 3.11
Classifier: Programming Language :: Python :: 3.12
License-File: LICENSE
Requires-Dist: aiohttp ~=3.9
Requires-Dist: beautifulsoup4 ~=4.12
Requires-Dist: furl
Requires-Dist: setuptools
